botmanager/__init__.py
botmanager/admin.py
botmanager/apps.py
botmanager/basetask.py
botmanager/models.py
botmanager/settings.py
botmanager/utils.py
botmanager/management/__init__.py
botmanager/management/commands/__init__.py
botmanager/management/commands/bot_manager.py
botmanager/migrations/0001_initial.py
botmanager/migrations/0002_auto_20161208_1406.py
botmanager/migrations/0003_auto_20161208_1529.py
botmanager/migrations/0004_auto_20161219_1931.py
botmanager/migrations/0005_task_parent.py
botmanager/migrations/0006_task_priority.py
botmanager/migrations/0007_task_is_persistent.py
botmanager/migrations/0008_auto_20170331_1752.py
botmanager/migrations/0009_task_extra_params.py
botmanager/migrations/0010_auto_20170531_1321.py
botmanager/migrations/0011_alter_task_create_dt_alter_task_id.py
botmanager/migrations/__init__.py
botmanager/templates/botmanager/task/change_form.html
django_botmanager-0.2.23.dist-info/licenses/LICENSE
django_botmanager-0.2.23.dist-info/METADATA
django_botmanager-0.2.23.dist-info/WHEEL
django_botmanager-0.2.23.dist-info/top_level.txt
django_botmanager-0.2.23.dist-info/RECORD
