Metadata-Version: 2.4
Name: django-botmanager
Version: 0.2.23
Summary: Async tasks for django
Home-page: https://github.com/dimoha/django-botmanager
Author: Dimoha
Author-email: dimoha@controlstyle.ru
License-File: LICENSE
Requires-Dist: setproctitle==1.1.10
Requires-Dist: jsonfield==3.1.0
Requires-Dist: psutil==5.8.0
Dynamic: author
Dynamic: author-email
Dynamic: home-page
Dynamic: license-file
Dynamic: requires-dist
Dynamic: summary
